{
  "schemaVersion": 1,
  "releaseMode": "npm-public-release-ready",
  "npm": {
    "publish": true,
    "registry": null,
    "access": "public",
    "tag": "latest",
    "packages": [
      "@kaelio/ktx"
    ]
  },
  "python": {
    "publish": false,
    "repository": null,
    "packages": [
      "kaelio-ktx"
    ]
  },
  "publishedPackageSmoke": {
    "packageName": "@kaelio/ktx",
    "version": "0.12.0",
    "registry": null
  },
  "runtimeInstaller": {
    "uvStrategy": "path-prerequisite",
    "bootstrapUv": false,
    "missingUvBehavior": "focused-error"
  },
  "requiredBeforePublishing": []
}
